controller/__init__.py
controller/controller_address.py
controller/controller_generic.py
controller/controller_person.py
model/__init__.py
model/dto.py
model/models.py
repository/__init__.py
repository/address_repository.py
repository/base.py
repository/person_repository.py
service/__init__.py
service/address_service.py
service/base.py
service/person_service.py
test_lib/__init__.py
test_lib/test_lib_main.py
util/__init__.py
util/database.py
crudpersonaddresslib2test-0.1.3.dist-info/METADATA
crudpersonaddresslib2test-0.1.3.dist-info/WHEEL
crudpersonaddresslib2test-0.1.3.dist-info/top_level.txt
crudpersonaddresslib2test-0.1.3.dist-info/RECORD
