Metadata-Version: 2.4
Name: CrudPersonAddressLIB2test
Version: 0.1.3
Summary: Biblioteca para crud+l de pessoas e endereços.
Home-page: https://github.com/magnagomatheus/fastAPI_mvc_generics_db.git
Author: Matheus de Oliveira Magnago
Author-email: magnagomatheus7@gmail.com
Classifier: Programming Language :: Python :: 3
Classifier: License :: OSI Approved :: MIT License
Classifier: Operating System :: OS Independent
Requires-Python: >=3.8
Dynamic: author
Dynamic: author-email
Dynamic: classifier
Dynamic: description
Dynamic: description-content-type
Dynamic: home-page
Dynamic: requires-python
Dynamic: summary
